gismath.cp311-win_amd64.pyd
gis3dtiles_helper-0.0.1a0.dist-info/METADATA
gis3dtiles_helper-0.0.1a0.dist-info/WHEEL
gis3dtiles_helper-0.0.1a0.dist-info/top_level.txt
gis3dtiles_helper-0.0.1a0.dist-info/RECORD
