Metadata-Version: 2.1
Name: gis3dtiles_helper
Version: 0.0.1a0
Summary: Just for gis3dtiles project
Author: Lun.A
Author-email: 517308447@qq.com
License: License :: OSI Approved :: Apache Software License
Classifier: Intended Audience :: Developers
Classifier: Development Status :: 2 - Pre-Alpha
Classifier: Programming Language :: Cython
Classifier: License :: OSI Approved :: Apache Software License
Classifier: Programming Language :: Python
Classifier: Programming Language :: Python :: 3.11
Classifier: Topic :: Scientific/Engineering
Classifier: Operating System :: POSIX
Classifier: Operating System :: MacOS
Classifier: Operating System :: Microsoft :: Windows :: Windows 11
Classifier: Topic :: Utilities
Requires-Dist: numpy>=2.1.0
Requires-Dist: shapely>=2.0.0
Requires-Dist: gismath>=0.0.30
